template_generator/__init__.py
template_generator/aigc_input.py
template_generator/binary.py
template_generator/convertor.py
template_generator/ffmpeg.py
template_generator/json_util.py
template_generator/license_manager.py
template_generator/main.py
template_generator/stats.py
template_generator/t2_to_t3.py
template_generator/template.py
template_generator/template_test.py
template_generator/utils.py
template_generator/bin/__init__.py
template_generator/bin/print_md5.py
template_generator/env/__init__.py
template_generator/env/setup_unified.sh.py
template_generator/env/template_env.py
template_generator/test/__init__.py
template_generator/test/tp_202511212.zip.py
p_template_generator-1.1.1.dist-info/METADATA
p_template_generator-1.1.1.dist-info/WHEEL
p_template_generator-1.1.1.dist-info/entry_points.txt
p_template_generator-1.1.1.dist-info/top_level.txt
p_template_generator-1.1.1.dist-info/RECORD
