Metadata-Version: 2.4
Name: p-template-generator
Version: 1.1.1
Summary: 跨平台视频模板生成器 - Python工具端
Author: Guangzhou Zhijian Technology Co., Ltd.
Author-email: mr_lonely@foxmail.com
Classifier: Programming Language :: Python :: 3
Classifier: License :: OSI Approved :: MIT License
Classifier: Operating System :: OS Independent
Requires-Python: >=3.7
Requires-Dist: requests
Requires-Dist: Image
Requires-Dist: protobuf
Requires-Dist: psutil
Requires-Dist: imagesize
Requires-Dist: urlparser
Requires-Dist: Pillow
Requires-Dist: p-template-res
Requires-Dist: orjson>=3.8.0
Dynamic: author
Dynamic: author-email
Dynamic: classifier
Dynamic: description
Dynamic: description-content-type
Dynamic: requires-dist
Dynamic: requires-python
Dynamic: summary
